Workbook

Sheet 入居者
A1: 居室 | B1: 利用者名
A2: 608 | B2: 岡村三男
A3: 703 | B3: 安藤静子
A4: 801
A5: 813 | B5: 奥谷國春
A6: 906 | B6: 藤本敏博
A7: 913 | B7: 加藤恵子
A8: 915 | B8: 菱池重治
A9: 1005
A10: 1006 | B10: 荒木のり子
A11: 1012
A12: 801✕ | B12: 上村春子

Sheet すまい請求書
A1: ええすまい請求書
A2: {=VLOOKUP(F$4,INDIRECT(M$2&"!A3:U109"),2,FALSE)} -> 荒木のり子 | E2: 様 | H2: 発行日： | J2: 46056 | M2: 202601
A4: マンションセレーネ（ええすまい） | F4: 1006 | G4: 号室 | H4: 株式会社AA 代表取締役 大石佐智子
M5: ※分割払いの管理
A6: ご請求金額 | C6: =I34 -> 113345 | H6: 大阪市西淀川区柏里2-9-3-102
A9: 内 容 | C9: 単 価 | E9: 数量 | G9: 小計 | I9: 備考
A10: {=INDIRECT(M$2&"!D2")} -> 家賃 | C10: {=VLOOKUP(F$4,INDIRECT(M$2&"!A3:Y109"),4,FALSE)} -> 40000 | E10: 1か月 | G10: =C10 -> 40000 | I10: =TEXT(EDATE(DATE(LEFT(M2,4), RIGHT(M2,2), 1), +1), "m月分") -> 2月分
A11: {=INDIRECT(M$2&"!E2")} -> 管理費 | C11: {=VLOOKUP(F$4,INDIRECT(M$2&"!A3:Y109"),5,FALSE)} -> 5000 | E11: 1か月 | G11: =C11 -> 5000 | I11: =TEXT(EDATE(DATE(LEFT(M2,4), RIGHT(M2,2), 1), +1), "m月分") -> 2月分
A12: {=INDIRECT(M$2&"!F2")} -> 共益費 | C12: {=VLOOKUP(F$4,INDIRECT(M$2&"!A3:Y109"),6,FALSE)} -> 5000 | E12: 1か月 | G12: =C12 -> 5000 | I12: =TEXT(EDATE(DATE(LEFT(M2,4), RIGHT(M2,2), 1), +1), "m月分") -> 2月分
A13: {=INDIRECT(M$2&"!G2")} -> 水道料金 | C13: {=VLOOKUP(F$4,INDIRECT(M$2&"!A3:Y109"),7,FALSE)} -> 2000 | E13: 1か月 | G13: =C13 -> 2000 | I13: =TEXT(EDATE(DATE(LEFT(M2,4), RIGHT(M2,2), 1), +1), "m月分") -> 2月分
A14: {=INDIRECT(M$2&"!H2")} -> 定額光熱費 | C14: {=VLOOKUP(F$4,INDIRECT(M$2&"!A3:Y109"),8,FALSE)} -> 10000 | E14: 1か月 | G14: =C14 -> 10000 | I14: =TEXT(EDATE(DATE(LEFT(M2,4), RIGHT(M2,2), 1), +1), "m月分") -> 2月分
A15: {=INDIRECT(M$2&"!I2")} -> 食事 | C15: {=VLOOKUP(F$4,INDIRECT(M$2&"!A3:Y109"),9,FALSE)} -> 31900 | E15: 1か月 | G15: =C15 -> 31900 | I15: =TEXT(EDATE(DATE(LEFT(M2,4), RIGHT(M2,2), 1), ), "m月分") -> 1月分
A16: {=INDIRECT(M$2&"!J2")} -> 調整額 | C16: {=VLOOKUP(F$4,INDIRECT(M$2&"!A3:Y109"),10,FALSE)} -> 0 | E16: 1か月 | G16: =C16 -> 0 | I16: =TEXT(EDATE(DATE(LEFT(M2,4), RIGHT(M2,2), 1), ), "m月分") -> 1月分
A17: {=INDIRECT(M$2&"!K2")} -> オムツ | C17: {=VLOOKUP(F$4,INDIRECT(M$2&"!A3:Y109"),11,FALSE)} | E17: 1か月 | G17: =C17 | I17: =TEXT(EDATE(DATE(LEFT(M2,4), RIGHT(M2,2), 1), ), "m月分") -> 1月分
A18: {=INDIRECT(M$2&"!L2")} -> 日用品 | C18: {=VLOOKUP(F$4,INDIRECT(M$2&"!A3:Y109"),12,FALSE)} -> 2263 | E18: 1か月 | G18: =C18 -> 2263 | I18: =TEXT(EDATE(DATE(LEFT(M2,4), RIGHT(M2,2), 1), ), "m月分") -> 1月分
A19: {=INDIRECT(M$2&"!M2")} -> 分割支払い | C19: {=VLOOKUP(F$4,INDIRECT(M$2&"!A3:Y109"),13,FALSE)} -> 10000 | E19: 1か月 | G19: =C19 -> 10000 | I19: =TEXT(EDATE(DATE(LEFT(M2,4), RIGHT(M2,2), 1), ), "m月分") -> 1月分
A20: {=INDIRECT(M$2&"!N2")} -> 事務手数料 | C20: {=VLOOKUP(F$4,INDIRECT(M$2&"!A3:Y109"),14,FALSE)} | E20: 1か月 | G20: =C20 | I20: =TEXT(EDATE(DATE(LEFT(M2,4), RIGHT(M2,2), 1), ), "m月分") -> 1月分
A21: {=INDIRECT(M$2&"!O2")} -> デイサービス | C21: {=VLOOKUP(F$4,INDIRECT(M$2&"!A3:Y109"),15,FALSE)} | E21: 1か月 | G21: =C21 | I21: =TEXT(EDATE(DATE(LEFT(M2,4), RIGHT(M2,2), 1), -1), "m月分") -> 12月分
A22: {=INDIRECT(M$2&"!P2")} -> 福祉用具 | C22: {=VLOOKUP(F$4,INDIRECT(M$2&"!A3:Y109"),16,FALSE)} | E22: 1か月 | G22: =C22 | I22: =TEXT(EDATE(DATE(LEFT(M2,4), RIGHT(M2,2), 1), -1), "m月分") -> 12月分
A23: {=INDIRECT(M$2&"!Q2")} -> しろくま薬局 | C23: {=VLOOKUP(F$4,INDIRECT(M$2&"!A3:Y109"),17,FALSE)} -> 7182 | E23: 1か月 | G23: =C23 -> 7182 | I23: =TEXT(EDATE(DATE(LEFT(M2,4), RIGHT(M2,2), 1), -1), "m月分") -> 12月分
A24: {=INDIRECT(M$2&"!R2")} -> 往診診療費 | C24: {=VLOOKUP(F$4,INDIRECT(M$2&"!A3:Y109"),18,FALSE)} | E24: 1か月 | G24: =C24 | I24: =TEXT(EDATE(DATE(LEFT(M2,4), RIGHT(M2,2), 1), -1), "m月分") -> 12月分
A25: {=INDIRECT(M$2&"!S2")} -> サポート費 | C25: {=VLOOKUP(F$4,INDIRECT(M$2&"!A3:Y109"),19,FALSE)} | E25: 1か月 | G25: =C25 | I25: =TEXT(EDATE(DATE(LEFT(M2,4), RIGHT(M2,2), 1), -1), "m月分") -> 12月分
A26: {=INDIRECT(M$2&"!T2")} -> その他 | C26: {=VLOOKUP(F$4,INDIRECT(M$2&"!A3:Y109"),20,FALSE)} | E26: 1か月 | G26: =C26
A27: {=INDIRECT(M$2&"!U2")} | C27: {=VLOOKUP(F$4,INDIRECT(M$2&"!A3:Y109"),21,FALSE)} | E27: 1か月 | G27: =C27
A28: {=INDIRECT(M$2&"!V2")} | C28: {=VLOOKUP(F$4,INDIRECT(M$2&"!A3:Y109"),22,FALSE)} | G28: =C28
A29: ご請求額合計 | G29: =SUM(G10:H28) -> 113345
A30: ※家賃、共益費、管理費、光熱費は消費税不要
A32: 8%対象 合計 | C32: 0 | G32: 消費税（８％） | I32: 0
A33: 10％対象 合計 | C33: 0 | G33: 消費税（10％） | I33: 0
G34: 税込合計 | I34: =G29 -> 113345

Sheet 領収書
B1: 領 収 書
E3: 受領日 | G3: 年 月 日
B4: ='すまい請求書'!A2 -> 荒木のり子 | D4: 様
C6: ='すまい請求書'!C6 -> 113345
B7: 但し 家賃、共益費、管理費、水道代、自費分として
C8: 上記の金額正に受領いたしました
C9: 株式会社AA
C10: 〒555-0022
C11: 大阪市西淀川区柏里2-9-3-102
C12: TEL・FAX 06-4400-2901

Sheet 領収書（手入力） 
B1: 領 収 書
E3: 受領日
B4: ='すまい請求書'!A2 -> 荒木のり子 | D4: 様
C6: 135000
B7: 但し 家賃、共益費、管理費、水道代、自費分として
C8: 上記の金額正に受領いたしました
C9: 株式会社AA
C10: 〒555-0022
C11: 大阪市西淀川区柏里2-9-3-102
C12: TEL・FAX 06-4400-2901

Sheet 合算請求書
A1: ご利用金額のお知らせ
A2: {=VLOOKUP(F$4,INDIRECT(M$2&"!A3:U109"),2,FALSE)} -> 荒木のり子 | E2: 様 | F2: 発行日： | H2: 46056 | M2: 202601
A4: マンションセレーネ（ええすまい） | F4: 1006 | G4: 号室
B7: 合計金額 | D7: =SUM(C10:C12) -> 135000
A9: 内 容 | C9: 請求金額 | E9: お支払期限 | G9: 備考
A10: ええすまい | C10: {=VLOOKUP(F$4,INDIRECT(M$2&"!A3:Y109"),23,FALSE)} -> 113345 | E10: =H2+20 -> 46076 | G10: 請求書別紙
A11: ええかいご | C11: {=VLOOKUP(F$4,INDIRECT(M$2&"!A3:Y109"),24,FALSE)} -> 21655 | E11: =H2+20 -> 46076 | G11: 請求書別紙
A12: ええかんご | C12: {=VLOOKUP(F$4,INDIRECT(M$2&"!A3:Y109"),25,FALSE)} | E12: =H2+25 -> 46081 | G12: 請求書別紙
A14: お支払につきましては下記口座へお願いいたします。
A15: 振込手数料につきましてはお客様ご負担にてお願い申し上げます。
A17: ■振込先
A18: 銀行名： | C18: 住信ＳＢＩネット銀行（金融機関コード0038）
A19: 支店名： | C19: 法人第一支店（支店コード106）
A20: 口座番号： | C20: 普通 2555848
A21: 口座名義： | C21: 株式会社AA ええすまい塚本
C22: カ）エーエー

Sheet 202602
A1: 46081 | C1: 請求 | D1: D | E1: E | F1: F | G1: G | H1: H | I1: I | J1: J | K1: K | L1: L | M1: M | N1: N | O1: O | P1: P | Q1: Q | R1: R | S1: S | T1: T | U1: U | V1: V | W1: W | X1: X | Y1: Y | Z1: Z | AA1: AA | AB1: AB
A2: 居室 | B2: 利用者名 | C2: 分納残 | D2: 家賃 | E2: 管理費 | F2: 共益費 | G2: 水道料金 | H2: 定額光熱費 | I2: 食事 | J2: 調整額 | K2: オムツ | L2: 日用品 | M2: 分割支払い | N2: 事務手数料 | O2: デイサービス | P2: 福祉用具 | Q2: しろくま薬局 | R2: 往診診療費 | S2: サポート費 | T2: その他 | W2: 計 | X2: 一部負担(介護) | Y2: 一部負担(看護) | Z2: 合計 | AA2: 備考 | AB2: 請求書 | AC2: 分割残高
A3: 608 | B3: 岡村三男 | D3: 40000 | E3: 5000 | F3: 5000 | G3: 2000 | H3: 10000 | K3: 0 | L3: 0 | W3: =SUM(D3:V3) -> 62000 | Z3: =SUM(W3:Y3) -> 62000 | AB3: 未作成 | AC3: =C3-M3 -> 0
A4: 703 | B4: 安藤静子 | D4: 40000 | E4: 5000 | F4: 5000 | G4: 2000 | H4: 10000 | I4: 12100 | J4: =IF(90000 - (SUM(D4:I4, K4:V4) + X4 + Y4) > 0, 0, 90000 - (SUM(D4:I4, K4:V4) + X4 + Y4)) -> -48384 | K4: 7986 | L4: 1606 | Q4: 4612 | W4: =SUM(D4:V4) -> 39920 | X4: 39580 | Y4: =8000+2500 -> 10500 | Z4: =SUM(W4:Y4) -> 90000 | AA4: 9〇 | AB4: 未作成 | AC4: =C4-M4 -> 0
A5: 801 | D5: 0 | E5: 0 | F5: 0 | G5: 0 | H5: 0 | W5: =SUM(D5:V5) -> 0 | Z5: =SUM(W5:Y5) -> 0 | AB5: 未作成 | AC5: 0
A6: 813 | B6: 奥谷國治 | D6: 40000 | E6: 5000 | F6: 5000 | G6: 2000 | H6: 10000 | W6: =SUM(D6:V6) -> 62000 | Z6: =SUM(W6:Y6) -> 62000 | AA6: 3〇 | AB6: 未作成 | AC6: =C6-M6 -> 0
A7: 906 | B7: 藤本敏博 | C7: 62000 | D7: 40000 | E7: 5000 | F7: 5000 | G7: 2000 | H7: 10000 | I7: 35640 | J7: =IF(110000 - (SUM(D7:I7, K7:V7) + X7 + Y7) > 0, 0, 110000 - (SUM(D7:I7, K7:V7) + X7 + Y7)) -> -37883 | L7: 2044 | M7: 10000 | O7: 17076 | W7: =SUM(D7:V7) -> 88877 | X7: 16123 | Y7: 5000 | Z7: =SUM(W7:Y7) -> 110000 | AA7: 11○ | AB7: 未作成 | AC7: =C7-M7 -> 52000
A8: 913 | B8: 加藤敬子 | C8: 47000 | D8: 40000 | E8: 5000 | F8: 5000 | G8: 2000 | H8: 10000 | I8: 37290 | J8: =IF(110000 - (SUM(D8:I8, K8:V8) + X8 + Y8) > 0, 0, 110000 - (SUM(D8:I8, K8:V8) + X8 + Y8)) -> -49152 | K8: 10164 | L8: 2044 | M8: 10000 | O8: 12192 | Q8: 3292 | W8: =SUM(D8:V8) -> 87830 | X8: 22170 | Z8: =SUM(W8:Y8) -> 110000 | AA8: 10〇+初期1万 | AB8: 未作成 | AC8: =C8-M8 -> 37000
A9: 915 | B9: 菱池重治 | C9: 110000 | D9: 0 | E9: 0 | F9: 0 | G9: 0 | H9: 0 | M9: 10000 | W9: =SUM(D9:V9) -> 10000 | Z9: =SUM(W9:Y9) -> 10000 | AA9: 13 | AB9: 未作成 | AC9: =C9-M9 -> 100000
A10: 1005 | W10: =SUM(D10:V10) -> 0 | Z10: =SUM(W10:Y10) -> 0 | AB10: 未作成 | AC10: =C10-M10 -> 0
A11: 1006 | B11: 荒木のり子 | C11: 110000 | D11: 40000 | E11: 5000 | F11: 5000 | G11: 2000 | H11: 10000 | I11: 30800 | J11: =IF(150000 - (SUM(D11:I11, K11:V11) + X11 + Y11) > 0, 0, 150000 - (SUM(D11:I11, K11:V11) + X11 + Y11)) -> 0 | L11: 2044 | M11: 10000 | Q11: 4732 | W11: =SUM(D11:V11) -> 109576 | X11: 21534 | Z11: =SUM(W11:Y11) -> 131110 | AA11: 13-15 | AB11: 未作成 | AC11: =C11-M11 -> 100000
A12: 1012 | W12: =SUM(D12:V12) -> 0 | Z12: =SUM(W12:Y12) -> 0 | AB12: 未作成 | AC12: =C12-M12 -> 0
W13: =SUM(D13:V13) -> 0 | Z13: =SUM(W13:Y13) -> 0 | AB13: 未作成 | AC13: =C13-M13 -> 0
A14: ='入居者'!A13 | W14: =SUM(D14:V14) -> 0 | Z14: =SUM(W14:Y14) -> 0 | AC14: =C14-M14 -> 0
W15: =SUM(D15:V15) -> 0 | Z15: =SUM(W15:Y15) -> 0 | AC15: =C15-M15 -> 0
W16: =SUM(D16:V16) -> 0 | Z16: =SUM(W16:Y16) -> 0 | AC16: =C16-M16 -> 0
W17: =SUM(D17:V17) -> 0 | Z17: =SUM(W17:Y17) -> 0 | AC17: =C17-M17 -> 0
W18: =SUM(D18:V18) -> 0 | Z18: =SUM(W18:Y18) -> 0 | AC18: =C18-M18 -> 0
W19: =SUM(D19:V19) -> 0 | Z19: =SUM(W19:Y19) -> 0 | AC19: =C19-M19 -> 0
W20: =SUM(D20:V20) -> 0 | Z20: =SUM(W20:Y20) -> 0 | AC20: =C20-M20 -> 0
W21: =SUM(D21:V21) -> 0 | Z21: =SUM(W21:Y21) -> 0 | AC21: =C21-M21 -> 0
W22: =SUM(D22:V22) -> 0 | Z22: =SUM(W22:Y22) -> 0 | AC22: =C22-M22 -> 0
W23: =SUM(D23:V23) -> 0 | Z23: =SUM(W23:Y23) -> 0 | AC23: =C23-M23 -> 0
W24: =SUM(D24:V24) -> 0 | Z24: =SUM(W24:Y24) -> 0 | AC24: =C24-M24 -> 0
W25: =SUM(D25:V25) -> 0 | Z25: =SUM(W25:Y25) -> 0 | AC25: =C25-M25 -> 0
W26: =SUM(D26:V26) -> 0 | Z26: =SUM(W26:Y26) -> 0 | AC26: =C26-M26 -> 0
... W109: =SUM(D109:V109) -> 0 | Z109: =SUM(W109:Y109) -> 0 | AC109: =C109-M109 -> 0
A110: 合計 | D110: =SUM(D3:D109) -> 240000 | E110: =SUM(E3:E109) -> 30000 | F110: =SUM(F3:F109) -> 30000 | G110: =SUM(G3:G109) -> 12000 | H110: =SUM(H3:H109) -> 60000 | I110: =SUM(I3:I109) -> 115830 | J110: =SUM(J3:J109) -> -135419 | K110: =SUM(K3:K109) -> 18150 | ... V110: =SUM(V3:V109) -> 0 | W110: =SUM(D110:V110) -> 460203 | X110: =SUM(X3:X109) -> 99407 | Y110: =SUM(Y3:Y109) -> 15500 | Z110: =SUM(Z3:Z109) -> 575110

Sheet 202601
A1: 46053 | C1: 請求 | D1: D | E1: E | F1: F | G1: G | H1: H | I1: I | J1: J | K1: K | L1: L | M1: M | N1: N | O1: O | P1: P | Q1: Q | R1: R | S1: S | T1: T | U1: U | V1: V | W1: W | X1: X | Y1: Y | Z1: Z | AA1: AA | AB1: AB
A2: 居室 | B2: 利用者名 | C2: 分納残 | D2: 家賃 | E2: 管理費 | F2: 共益費 | G2: 水道料金 | H2: 定額光熱費 | I2: 食事 | J2: 調整額 | K2: オムツ | L2: 日用品 | M2: 分割支払い | N2: 事務手数料 | O2: デイサービス | P2: 福祉用具 | Q2: しろくま薬局 | R2: 往診診療費 | S2: サポート費 | T2: その他 | W2: 計 | X2: 一部負担(介護) | Y2: 一部負担(看護) | Z2: 合計 | AA2: 備考 | AB2: 請求書 | AC2: 分割残高
A3: 608 | B3: 岡村三男 | D3: 40000 | E3: 5000 | F3: 5000 | G3: 2000 | H3: 10000 | K3: 0 | L3: 0 | W3: =SUM(D3:V3) -> 62000 | Z3: =SUM(W3:Y3) -> 62000 | AB3: 未作成 | AC3: =C3-M3 -> 0
A4: 703 | B4: 安藤静子 | D4: 40000 | E4: 5000 | F4: 5000 | G4: 2000 | H4: 10000 | I4: 16500 | J4: =IF(90000 - (SUM(D4:I4, K4:V4) + X4 + Y4) > 0, 0, 90000 - (SUM(D4:I4, K4:V4) + X4 + Y4)) -> -45578 | K4: 11253 | L4: 2263 | Q4: 3982 | W4: =SUM(D4:V4) -> 50420 | X4: 39580 | Z4: =SUM(W4:Y4) -> 90000 | AA4: 9〇 | AB4: 未作成 | AC4: =C4-M4 -> 0
A5: 801 | D5: 0 | E5: 0 | F5: 0 | G5: 0 | H5: 0 | W5: =SUM(D5:V5) -> 0 | Z5: =SUM(W5:Y5) -> 0 | AB5: 未作成 | AC5: 0
A6: 813 | B6: 奥谷國治 | D6: 40000 | E6: 5000 | F6: 5000 | G6: 2000 | H6: 10000 | W6: =SUM(D6:V6) -> 62000 | Z6: =SUM(W6:Y6) -> 62000 | AA6: 3〇 | AB6: 未作成 | AC6: =C6-M6 -> 0
A7: 906 | B7: 藤本敏博 | C7: 62000 | D7: 40000 | E7: 5000 | F7: 5000 | G7: 2000 | H7: 10000 | I7: 42900 | J7: =IF(110000 - (SUM(D7:I7, K7:V7) + X7 + Y7) > 0, 0, 110000 - (SUM(D7:I7, K7:V7) + X7 + Y7)) -> -32266 | L7: 2263 | M7: 10000 | W7: =SUM(D7:V7) -> 84897 | X7: 20103 | Y7: 5000 | Z7: =SUM(W7:Y7) -> 110000 | AA7: 11○ | AB7: 未作成 | AC7: =C7-M7 -> 52000
A8: 913 | B8: 加藤敬子 | C8: 47000 | D8: 40000 | E8: 5000 | F8: 5000 | G8: 2000 | H8: 10000 | I8: 39380 | J8: =IF(110000 - (SUM(D8:I8, K8:V8) + X8 + Y8) > 0, 0, 110000 - (SUM(D8:I8, K8:V8) + X8 + Y8)) -> -55991 | K8: 11253 | L8: 2263 | M8: 10000 | O8: 12192 | Q8: 6662 | W8: =SUM(D8:V8) -> 87759 | X8: 22241 | Z8: =SUM(W8:Y8) -> 110000 | AA8: 10〇+初期1万 | AB8: 未作成 | AC8: =C8-M8 -> 37000
A9: 915 | B9: 菱池重治 | C9: 110000 | D9: 0 | E9: 0 | F9: 0 | G9: 0 | H9: 0 | M9: 10000 | Q9: 3460 | W9: =SUM(D9:V9) -> 13460 | X9: 3541 | Z9: =SUM(W9:Y9) -> 17001 | AA9: 13 | AB9: 未作成 | AC9: =C9-M9 -> 100000
A10: 1005 | W10: =SUM(D10:V10) -> 0 | Z10: =SUM(W10:Y10) -> 0 | AB10: 未作成 | AC10: =C10-M10 -> 0
A11: 1006 | B11: 荒木のり子 | C11: 110000 | D11: 40000 | E11: 5000 | F11: 5000 | G11: 2000 | H11: 10000 | I11: 31900 | J11: =IF(150000 - (SUM(D11:I11, K11:V11) + X11 + Y11) > 0, 0, 150000 - (SUM(D11:I11, K11:V11) + X11 + Y11)) -> 0 | L11: 2263 | M11: 10000 | Q11: 7182 | W11: =SUM(D11:V11) -> 113345 | X11: 21655 | Z11: =SUM(W11:Y11) -> 135000 | AA11: 13-15 | AB11: 未作成 | AC11: =C11-M11 -> 100000
A12: 1012 | W12: =SUM(D12:V12) -> 0 | Z12: =SUM(W12:Y12) -> 0 | AB12: 未作成 | AC12: =C12-M12 -> 0
W13: =SUM(D13:V13) -> 0 | Z13: =SUM(W13:Y13) -> 0 | AB13: 未作成 | AC13: =C13-M13 -> 0
A14: ='入居者'!A13 | W14: =SUM(D14:V14) -> 0 | Z14: =SUM(W14:Y14) -> 0 | AC14: =C14-M14 -> 0
W15: =SUM(D15:V15) -> 0 | Z15: =SUM(W15:Y15) -> 0 | AC15: =C15-M15 -> 0
W16: =SUM(D16:V16) -> 0 | Z16: =SUM(W16:Y16) -> 0 | AC16: =C16-M16 -> 0
W17: =SUM(D17:V17) -> 0 | Z17: =SUM(W17:Y17) -> 0 | AC17: =C17-M17 -> 0
W18: =SUM(D18:V18) -> 0 | Z18: =SUM(W18:Y18) -> 0 | AC18: =C18-M18 -> 0
W19: =SUM(D19:V19) -> 0 | Z19: =SUM(W19:Y19) -> 0 | AC19: =C19-M19 -> 0
W20: =SUM(D20:V20) -> 0 | Z20: =SUM(W20:Y20) -> 0 | AC20: =C20-M20 -> 0
W21: =SUM(D21:V21) -> 0 | Z21: =SUM(W21:Y21) -> 0 | AC21: =C21-M21 -> 0
W22: =SUM(D22:V22) -> 0 | Z22: =SUM(W22:Y22) -> 0 | AC22: =C22-M22 -> 0
W23: =SUM(D23:V23) -> 0 | Z23: =SUM(W23:Y23) -> 0 | AC23: =C23-M23 -> 0
W24: =SUM(D24:V24) -> 0 | Z24: =SUM(W24:Y24) -> 0 | AC24: =C24-M24 -> 0
W25: =SUM(D25:V25) -> 0 | Z25: =SUM(W25:Y25) -> 0 | AC25: =C25-M25 -> 0
W26: =SUM(D26:V26) -> 0 | Z26: =SUM(W26:Y26) -> 0 | AC26: =C26-M26 -> 0
... W109: =SUM(D109:V109) -> 0 | Z109: =SUM(W109:Y109) -> 0 | AC109: =C109-M109 -> 0
A110: 合計 | D110: =SUM(D3:D109) -> 240000 | E110: =SUM(E3:E109) -> 30000 | F110: =SUM(F3:F109) -> 30000 | G110: =SUM(G3:G109) -> 12000 | H110: =SUM(H3:H109) -> 60000 | I110: =SUM(I3:I109) -> 130680 | J110: =SUM(J3:J109) -> -133835 | K110: =SUM(K3:K109) -> 22506 | ... V110: =SUM(V3:V109) -> 0 | W110: =SUM(D110:V110) -> 473881 | X110: =SUM(X3:X109) -> 107120 | Y110: =SUM(Y3:Y109) -> 5000 | Z110: =SUM(Z3:Z109) -> 586001

Sheet 202512
A1: 46022 | C1: 請求 | D1: D | E1: E | F1: F | G1: G | H1: H | I1: I | J1: J | K1: K | L1: L | M1: M | N1: N | O1: O | P1: P | Q1: Q | R1: R | S1: S | T1: T | U1: U | V1: V | W1: W | X1: X | Y1: Y | Z1: Z | AA1: AA | AB1: AB
A2: 居室 | B2: 利用者名 | C2: 分納残 | D2: 家賃 | E2: 管理費 | F2: 共益費 | G2: 水道料金 | H2: 定額光熱費 | I2: 食事 | J2: 調整額 | K2: オムツ | L2: 日用品 | M2: 分割支払い | N2: 事務手数料 | O2: デイサービス | P2: 福祉用具 | Q2: しろくま薬局 | R2: 往診診療費 | S2: サポート費 | T2: その他 | W2: 計 | X2: 一部負担(介護) | Y2: 一部負担(看護) | Z2: 合計 | AA2: 備考 | AB2: 請求書 | AC2: 分割残高
A3: 608 | B3: 岡村三男 | D3: 40000 | E3: 5000 | F3: 5000 | G3: 2000 | H3: 10000 | K3: 0 | L3: 0 | Q3: 31998 | W3: =SUM(D3:V3) -> 93998 | X3: 23519 | Y3: 8000 | Z3: =SUM(W3:Y3) -> 125517 | AB3: 未作成 | AC3: =C3-M3 -> 0
A4: 703 | B4: 安藤静子 | D4: 40000 | E4: 5000 | F4: 5000 | G4: 2000 | H4: 10000 | I4: 32450 | J4: -68872 | K4: 11253 | L4: 2263 | Q4: 11255 | W4: =SUM(D4:V4) -> 50349 | X4: 39651 | Z4: =SUM(W4:Y4) -> 90000 | AA4: 9〇 | AB4: 未作成 | AC4: =C4-M4 -> 0
A5: 801 | B5: 櫻井榮治 | D5: 0 | E5: 0 | F5: 0 | G5: 0 | H5: 0 | Q5: 5114 | W5: =SUM(D5:V5) -> 5114 | X5: 26202 | Z5: =SUM(W5:Y5) -> 31316 | AB5: 未作成 | AC5: 0
A6: 813 | B6: 奥谷國治 | D6: 40000 | E6: 5000 | F6: 5000 | G6: 2000 | H6: 10000 | J6: -32000 | W6: =SUM(D6:V6) -> 30000 | Z6: =SUM(W6:Y6) -> 30000 | AA6: 3〇 | AB6: 未作成 | AC6: =C6-M6 -> 0
A7: 906 | B7: 藤本敏博 | C7: 72000 | D7: 40000 | E7: 5000 | F7: 5000 | G7: 2000 | H7: 10000 | I7: 39930 | J7: -29061 | L7: 2263 | M7: 10000 | W7: =SUM(D7:V7) -> 85132 | X7: 19868 | Y7: 5000 | Z7: =SUM(W7:Y7) -> 110000 | AA7: 11○ | AB7: 未作成 | AC7: =C7-M7 -> 62000
A8: 913 | B8: 加藤敬子 | C8: 47000 | D8: 40000 | E8: 5000 | F8: 5000 | G8: 2000 | H8: 10000 | I8: 39380 | J8: -59513 | K8: 11253 | L8: 2263 | M8: 10000 | O8: 18286 | Q8: 3562 | W8: =SUM(D8:V8) -> 87231 | X8: 22769 | Z8: =SUM(W8:Y8) -> 110000 | AA8: 10〇+初期1万 | AB8: 未作成 | AC8: =C8-M8 -> 37000
A9: 915 | B9: 菱池重治 | C9: 110000 | D9: 0 | E9: 0 | F9: 0 | G9: 0 | H9: 0 | I9: 4290 | K9: 484 | L9: 292 | M9: 10000 | Q9: 25702 | W9: =SUM(D9:V9) -> 40768 | X9: 29823 | Z9: =SUM(W9:Y9) -> 70591 | AA9: 13 | AB9: 未作成 | AC9: =C9-M9 -> 100000
A10: 1005 | W10: =SUM(D10:V10) -> 0 | Z10: =SUM(W10:Y10) -> 0 | AB10: 未作成 | AC10: =C10-M10 -> 0
A11: 1006 | B11: 荒木のり子 | C11: 120000 | D11: 40000 | E11: 5000 | F11: 5000 | G11: 2000 | H11: 10000 | I11: 29700 | K11: 0 | L11: 0 | M11: 10000 | Q11: 20334 | W11: =SUM(D11:V11) -> 122034 | Z11: =SUM(W11:Y11) -> 122034 | AA11: 13-15 | AB11: 未作成 | AC11: =C11-M11 -> 110000
A12: 1012 | W12: =SUM(D12:V12) -> 0 | Z12: =SUM(W12:Y12) -> 0 | AB12: 未作成 | AC12: =C12-M12 -> 0
W13: =SUM(D13:V13) -> 0 | Z13: =SUM(W13:Y13) -> 0 | AB13: 未作成 | AC13: =C13-M13 -> 0
A14: ='入居者'!A13 | W14: =SUM(D14:V14) -> 0 | Z14: =SUM(W14:Y14) -> 0 | AC14: =C14-M14 -> 0
W15: =SUM(D15:V15) -> 0 | Z15: =SUM(W15:Y15) -> 0 | AC15: =C15-M15 -> 0
W16: =SUM(D16:V16) -> 0 | Z16: =SUM(W16:Y16) -> 0 | AC16: =C16-M16 -> 0
W17: =SUM(D17:V17) -> 0 | Z17: =SUM(W17:Y17) -> 0 | AC17: =C17-M17 -> 0
W18: =SUM(D18:V18) -> 0 | Z18: =SUM(W18:Y18) -> 0 | AC18: =C18-M18 -> 0
W19: =SUM(D19:V19) -> 0 | Z19: =SUM(W19:Y19) -> 0 | AC19: =C19-M19 -> 0
W20: =SUM(D20:V20) -> 0 | Z20: =SUM(W20:Y20) -> 0 | AC20: =C20-M20 -> 0
W21: =SUM(D21:V21) -> 0 | Z21: =SUM(W21:Y21) -> 0 | AC21: =C21-M21 -> 0
W22: =SUM(D22:V22) -> 0 | Z22: =SUM(W22:Y22) -> 0 | AC22: =C22-M22 -> 0
W23: =SUM(D23:V23) -> 0 | Z23: =SUM(W23:Y23) -> 0 | AC23: =C23-M23 -> 0
W24: =SUM(D24:V24) -> 0 | Z24: =SUM(W24:Y24) -> 0 | AC24: =C24-M24 -> 0
W25: =SUM(D25:V25) -> 0 | Z25: =SUM(W25:Y25) -> 0 | AC25: =C25-M25 -> 0
W26: =SUM(D26:V26) -> 0 | Z26: =SUM(W26:Y26) -> 0 | AC26: =C26-M26 -> 0
... W109: =SUM(D109:V109) -> 0 | Z109: =SUM(W109:Y109) -> 0 | AC109: =C109-M109 -> 0
A110: 合計 | D110: =SUM(D3:D109) -> 240000 | E110: =SUM(E3:E109) -> 30000 | F110: =SUM(F3:F109) -> 30000 | G110: =SUM(G3:G109) -> 12000 | H110: =SUM(H3:H109) -> 60000 | I110: =SUM(I3:I109) -> 145750 | J110: =SUM(J3:J109) -> -189446 | K110: =SUM(K3:K109) -> 22990 | ... V110: =SUM(V3:V109) -> 0 | W110: =SUM(D110:V110) -> 514626 | X110: =SUM(X3:X109) -> 161832 | Y110: =SUM(Y3:Y109) -> 13000 | Z110: =SUM(Z3:Z109) -> 689458

Sheet 202511
A1: 45991 | C1: 請求 | D1: D | E1: E | F1: F | G1: G | H1: H | I1: I | J1: J | K1: K | L1: L | M1: M | N1: N | O1: O | P1: P | Q1: Q | R1: R | S1: S | T1: T | U1: U | V1: V | W1: W | X1: X | Y1: Y | Z1: Z | AA1: AA | AB1: AB
A2: 居室 | B2: 利用者名 | C2: 分納残 | D2: 家賃 | E2: 管理費 | F2: 共益費 | G2: 水道料金 | H2: 定額光熱費 | I2: 食事 | J2: 調整額 | K2: オムツ | L2: 日用品 | M2: 分割支払い | N2: 事務手数料 | O2: デイサービス | P2: 福祉用具 | Q2: しろくま薬局 | R2: 往診診療費 | S2: サポート費 | T2: その他 | W2: 計 | X2: 一部負担(介護) | Y2: 一部負担(看護) | Z2: 合計 | AA2: 備考 | AB2: 請求書 | AC2: 分割残高
A3: 608 | B3: 岡村三男 | D3: 40000 | E3: 5000 | F3: 5000 | G3: 2000 | H3: 10000 | K3: 0 | L3: 0 | W3: =SUM(D3:V3) -> 62000 | X3: 23993 | Y3: 8000 | Z3: =SUM(W3:Y3) -> 93993 | AB3: 未作成 | AC3: =C3-M3 -> 0
A4: 703 | B4: 安藤静子 | D4: 40000 | E4: 5000 | F4: 5000 | G4: 2000 | H4: 10000 | I4: 1650 | J4: -21330 | W4: =SUM(D4:V4) -> 42320 | X4: 39680 | Y4: 8000 | Z4: =SUM(W4:Y4) -> 90000 | AA4: 9〇 | AB4: 未作成 | AC4: =C4-M4 -> 0
A5: 801 | B5: 櫻井榮治 | D5: 0 | E5: 0 | F5: 0 | G5: 0 | H5: 10000 | I5: 31460 | K5: 8395 | L5: 2190 | Q5: 6432 | W5: =SUM(D5:V5) -> 58477 | X5: 36518 | Z5: =SUM(W5:Y5) -> 94995 | AB5: 未作成 | AC5: 0
A6: 813 | B6: 奥谷國治 | D6: 40000 | E6: 5000 | F6: 5000 | G6: 2000 | H6: 10000 | W6: =SUM(D6:V6) -> 62000 | Z6: =SUM(W6:Y6) -> 62000 | AA6: 3〇 | AB6: 未作成 | AC6: =C6-M6 -> 0
A7: 906 | W7: =SUM(D7:V7) -> 0 | Z7: =SUM(W7:Y7) -> 0 | AB7: 未作成 | AC7: =C7-M7 -> 0
A8: 913 | B8: 加藤敬子 | C8: 57000 | D8: 40000 | E8: 5000 | F8: 5000 | G8: 2000 | H8: 10000 | I8: 38500 | J8: -50697 | K8: 10890 | L8: 2190 | M8: 10000 | O8: 7281 | Q8: 4722 | W8: =SUM(D8:V8) -> 84886 | X8: 25114 | Z8: =SUM(W8:Y8) -> 110000 | AA8: 10〇+初期1万 | AB8: 未作成 | AC8: =C8-M8 -> 47000
A9: 915 | B9: 菱池重治 | C9: 120000 | D9: 40000 | E9: 5000 | F9: 5000 | G9: 2000 | H9: 10000 | I9: 38280 | J9: 4565 | K9: 3630 | L9: 2190 | M9: 10000 | W9: =SUM(D9:V9) -> 120665 | X9: 9335 | Z9: =SUM(W9:Y9) -> 130000 | AA9: 13 | AB9: 未作成 | AC9: =C9-M9 -> 110000
A10: 1005 | W10: =SUM(D10:V10) -> 0 | Z10: =SUM(W10:Y10) -> 0 | AB10: 未作成 | AC10: =C10-M10 -> 0
A11: 1006 | B11: 荒木のり子 | C11: 130000 | D11: 40000 | E11: 5000 | F11: 5000 | G11: 2000 | H11: 10000 | I11: 31900 | K11: 0 | L11: 0 | M11: 10000 | W11: =SUM(D11:V11) -> 103900 | Z11: =SUM(W11:Y11) -> 103900 | AA11: 13-15 | AB11: 未作成 | AC11: =C11-M11 -> 120000
A12: 1012 | W12: =SUM(D12:V12) -> 0 | Z12: =SUM(W12:Y12) -> 0 | AB12: 未作成 | AC12: =C12-M12 -> 0
W13: =SUM(D13:V13) -> 0 | Z13: =SUM(W13:Y13) -> 0 | AB13: 未作成 | AC13: =C13-M13 -> 0
A14: ='入居者'!A13 | W14: =SUM(D14:V14) -> 0 | Z14: =SUM(W14:Y14) -> 0 | AC14: =C14-M14 -> 0
W15: =SUM(D15:V15) -> 0 | Z15: =SUM(W15:Y15) -> 0 | AC15: =C15-M15 -> 0
W16: =SUM(D16:V16) -> 0 | Z16: =SUM(W16:Y16) -> 0 | AC16: =C16-M16 -> 0
W17: =SUM(D17:V17) -> 0 | Z17: =SUM(W17:Y17) -> 0 | AC17: =C17-M17 -> 0
W18: =SUM(D18:V18) -> 0 | Z18: =SUM(W18:Y18) -> 0 | AC18: =C18-M18 -> 0
W19: =SUM(D19:V19) -> 0 | Z19: =SUM(W19:Y19) -> 0 | AC19: =C19-M19 -> 0
W20: =SUM(D20:V20) -> 0 | Z20: =SUM(W20:Y20) -> 0 | AC20: =C20-M20 -> 0
W21: =SUM(D21:V21) -> 0 | Z21: =SUM(W21:Y21) -> 0 | AC21: =C21-M21 -> 0
W22: =SUM(D22:V22) -> 0 | Z22: =SUM(W22:Y22) -> 0 | AC22: =C22-M22 -> 0
W23: =SUM(D23:V23) -> 0 | Z23: =SUM(W23:Y23) -> 0 | AC23: =C23-M23 -> 0
W24: =SUM(D24:V24) -> 0 | Z24: =SUM(W24:Y24) -> 0 | AC24: =C24-M24 -> 0
W25: =SUM(D25:V25) -> 0 | Z25: =SUM(W25:Y25) -> 0 | AC25: =C25-M25 -> 0
W26: =SUM(D26:V26) -> 0 | Z26: =SUM(W26:Y26) -> 0 | AC26: =C26-M26 -> 0
... W109: =SUM(D109:V109) -> 0 | Z109: =SUM(W109:Y109) -> 0 | AC109: =C109-M109 -> 0
A110: 合計 | D110: =SUM(D3:D109) -> 240000 | E110: =SUM(E3:E109) -> 30000 | F110: =SUM(F3:F109) -> 30000 | G110: =SUM(G3:G109) -> 12000 | H110: =SUM(H3:H109) -> 70000 | I110: =SUM(I3:I109) -> 141790 | J110: =SUM(J3:J109) -> -67462 | K110: =SUM(K3:K109) -> 22915 | ... V110: =SUM(V3:V109) -> 0 | W110: =SUM(D110:V110) -> 534248 | X110: =SUM(X3:X109) -> 134640 | Y110: =SUM(Y3:Y109) -> 16000 | Z110: =SUM(Z3:Z109) -> 684888

Sheet 202510
A1: 45961 | C1: 請求 | D1: D | E1: E | F1: F | G1: G | H1: H | I1: I | J1: J | K1: K | L1: L | M1: M | N1: N | O1: O | P1: P | Q1: Q | R1: R | S1: S | T1: T | U1: U | V1: V | W1: W | X1: X | Y1: Y | Z1: Z | AA1: AA | AB1: AB
A2: 居室 | B2: 利用者名 | C2: 分納残 | D2: 家賃 | E2: 管理費 | F2: 共益費 | G2: 水道料金 | H2: 定額光熱費 | I2: 食事 | J2: 調整額 | K2: オムツ | L2: 日用品 | M2: 分割支払い | N2: 事務手数料 | O2: デイサービス | P2: 福祉用具 | Q2: しろくま薬局 | R2: 往診診療費 | S2: サポート費 | T2: その他 | W2: 計 | X2: 一部負担(介護) | Y2: 一部負担(看護) | Z2: 合計 | AA2: 備考 | AB2: 請求書 | AC2: 分割残高
A3: 608 | B3: 岡村三男 | D3: 40000 | E3: 5000 | F3: 5000 | G3: 2000 | H3: 10000 | I3: 0 | K3: 0 | L3: 0 | W3: =SUM(D3:V3) -> 62000 | X3: 23525 | Y3: 8000 | Z3: =SUM(W3:Y3) -> 93525 | AB3: 未作成 | AC3: =C3-M3 -> 0
A4: 703 | B4: 安藤静子 | D4: 40000 | E4: 5000 | F4: 5000 | G4: 2000 | H4: 10000 | I4: 22330 | W4: =SUM(D4:V4) -> 84330 | Z4: =SUM(W4:Y4) -> 84330 | AA4: 9〇 | AB4: 未作成 | AC4: =C4-M4 -> 0
A5: 801 | B5: 櫻井榮治 | D5: 40000 | E5: 5000 | F5: 5000 | G5: 2000 | H5: 10000 | I5: 44330 | K5: 11253 | L5: 2263 | Q5: 5534 | W5: =SUM(D5:V5) -> 125380 | Z5: =SUM(W5:Y5) -> 125380 | AB5: 未作成 | AC5: 0
A6: 813 | B6: 奥谷國治 | D6: 40000 | E6: 5000 | F6: 5000 | G6: 2000 | H6: 10000 | I6: 30360 | W6: =SUM(D6:V6) -> 92360 | Z6: =SUM(W6:Y6) -> 92360 | AA6: 3〇 | AB6: 未作成 | AC6: =C6-M6 -> 0
A7: 906 | W7: =SUM(D7:V7) -> 0 | Z7: =SUM(W7:Y7) -> 0 | AB7: 未作成 | AC7: =C7-M7 -> 0
A8: 913 | B8: 加藤敬子 | C8: 67000 | D8: 40000 | E8: 5000 | F8: 5000 | G8: 2000 | H8: 10000 | I8: 41030 | J8: -46231 | K8: 11253 | L8: 2263 | M8: 10000 | Q8: 4642 | W8: =SUM(D8:V8) -> 84957 | X8: 25043 | Z8: =SUM(W8:Y8) -> 110000 | AA8: 10〇+初期1万 | AB8: 未作成 | AC8: =C8-M8 -> 57000
A9: 915 | B9: 菱池重治 | C9: 130000 | D9: 40000 | E9: 5000 | F9: 5000 | G9: 2000 | H9: 10000 | I9: 16060 | J9: 0 | K9: 1573 | L9: 949 | M9: 10000 | W9: =SUM(D9:V9) -> 90582 | X9: 25520 | Z9: =SUM(W9:Y9) -> 116102 | AA9: 45974 | AB9: 未作成 | AC9: =C9-M9 -> 120000
A10: 1005 | W10: =SUM(D10:V10) -> 0 | Z10: =SUM(W10:Y10) -> 0 | AB10: 未作成 | AC10: =C10-M10 -> 0
A11: 1006 | B11: 荒木のり子 | C11: 140000 | D11: 40000 | E11: 5000 | F11: 5000 | G11: 2000 | H11: 10000 | I11: 27500 | K11: 0 | L11: 0 | M11: 10000 | W11: =SUM(D11:V11) -> 99500 | Y11: =8780+14210 -> 22990 | Z11: =SUM(W11:Y11) -> 122490 | AA11: 13-15 | AB11: 未作成 | AC11: =C11-M11 -> 130000
A12: 1012 | W12: =SUM(D12:V12) -> 0 | Z12: =SUM(W12:Y12) -> 0 | AB12: 未作成 | AC12: =C12-M12 -> 0
W13: =SUM(D13:V13) -> 0 | Z13: =SUM(W13:Y13) -> 0 | AB13: 未作成 | AC13: =C13-M13 -> 0
A14: ='入居者'!A13 | W14: =SUM(D14:V14) -> 0 | Z14: =SUM(W14:Y14) -> 0 | AC14: =C14-M14 -> 0
W15: =SUM(D15:V15) -> 0 | Z15: =SUM(W15:Y15) -> 0 | AC15: =C15-M15 -> 0
W16: =SUM(D16:V16) -> 0 | Z16: =SUM(W16:Y16) -> 0 | AC16: =C16-M16 -> 0
W17: =SUM(D17:V17) -> 0 | Z17: =SUM(W17:Y17) -> 0 | AC17: =C17-M17 -> 0
W18: =SUM(D18:V18) -> 0 | Z18: =SUM(W18:Y18) -> 0 | AC18: =C18-M18 -> 0
W19: =SUM(D19:V19) -> 0 | Z19: =SUM(W19:Y19) -> 0 | AC19: =C19-M19 -> 0
W20: =SUM(D20:V20) -> 0 | Z20: =SUM(W20:Y20) -> 0 | AC20: =C20-M20 -> 0
W21: =SUM(D21:V21) -> 0 | Z21: =SUM(W21:Y21) -> 0 | AC21: =C21-M21 -> 0
W22: =SUM(D22:V22) -> 0 | Z22: =SUM(W22:Y22) -> 0 | AC22: =C22-M22 -> 0
W23: =SUM(D23:V23) -> 0 | Z23: =SUM(W23:Y23) -> 0 | AC23: =C23-M23 -> 0
W24: =SUM(D24:V24) -> 0 | Z24: =SUM(W24:Y24) -> 0 | AC24: =C24-M24 -> 0
W25: =SUM(D25:V25) -> 0 | Z25: =SUM(W25:Y25) -> 0 | AC25: =C25-M25 -> 0
W26: =SUM(D26:V26) -> 0 | Z26: =SUM(W26:Y26) -> 0 | AC26: =C26-M26 -> 0
... W109: =SUM(D109:V109) -> 0 | Z109: =SUM(W109:Y109) -> 0 | AC109: =C109-M109 -> 0
A110: 合計 | D110: =SUM(D3:D109) -> 280000 | E110: =SUM(E3:E109) -> 35000 | F110: =SUM(F3:F109) -> 35000 | G110: =SUM(G3:G109) -> 14000 | H110: =SUM(H3:H109) -> 70000 | I110: =SUM(I3:I109) -> 181610 | J110: =SUM(J3:J109) -> -46231 | K110: =SUM(K3:K109) -> 24079 | ... V110: =SUM(V3:V109) -> 0 | W110: =SUM(D110:V110) -> 639109 | X110: =SUM(X3:X109) -> 74088 | Y110: =SUM(Y3:Y109) -> 30990 | Z110: =SUM(Z3:Z109) -> 744187

Sheet 202509
A1: 45930 | C1: 請求 | D1: D | E1: E | F1: F | G1: G | H1: H | I1: I | J1: J | K1: K | L1: L | M1: M | N1: N | O1: O | P1: P | Q1: Q | R1: R | S1: S | T1: T | U1: U | V1: V | W1: W | X1: X | Y1: Y | Z1: Z | AA1: AA | AB1: AB
A2: 居室 | B2: 利用者名 | C2: 分納残 | D2: 家賃 | E2: 管理費 | F2: 共益費 | G2: 水道料金 | H2: 定額光熱費 | I2: 食事 | J2: 調整額 | K2: オムツ | L2: 日用品 | M2: 分割支払い | N2: 事務手数料 | O2: デイサービス | P2: 福祉用具 | Q2: しろくま薬局 | R2: 往診診療費 | S2: サポート費 | T2: その他 | W2: 計 | X2: 一部負担(介護) | Y2: 一部負担(看護) | Z2: 合計 | AA2: 備考 | AB2: 請求書 | AC2: 分割残高
A3: 608 | B3: 岡村三男 | D3: 40000 | E3: 5000 | F3: 5000 | G3: 2000 | H3: 10000 | I3: 0 | K3: 0 | L3: 0 | W3: =SUM(D3:V3) -> 62000 | X3: 23993 | Z3: =SUM(W3:Y3) -> 85993 | AB3: 未作成 | AC3: =C3-M3 -> 0
A4: 703 | B4: 安藤静子 | D4: 40000 | E4: 5000 | F4: 5000 | G4: 2000 | H4: 10000 | I4: 1100 | W4: =SUM(D4:V4) -> 63100 | Z4: =SUM(W4:Y4) -> 63100 | AB4: 未作成 | AC4: =C4-M4 -> 0
A5: 801 | B5: 櫻井榮治 | D5: 40000 | E5: 5000 | F5: 5000 | G5: 2000 | H5: 10000 | I5: 26840 | K5: 6897 | L5: 1387 | W5: =SUM(D5:V5) -> 97124 | Z5: =SUM(W5:Y5) -> 97124 | AB5: 未作成 | AC5: 0
A6: 813 | B6: 奥谷國治 | D6: 40000 | E6: 5000 | F6: 5000 | G6: 2000 | H6: 10000 | I6: 1100 | W6: =SUM(D6:V6) -> 63100 | Z6: =SUM(W6:Y6) -> 63100 | AB6: 未作成 | AC6: =C6-M6 -> 0
A7: 906 | W7: =SUM(D7:V7) -> 0 | Z7: =SUM(W7:Y7) -> 0 | AB7: 未作成 | AC7: =C7-M7 -> 0
A8: 913 | B8: 加藤敬子 | C8: 77000 | D8: 40000 | E8: 5000 | F8: 5000 | G8: 2000 | H8: 10000 | I8: 40150 | J8: -83160 | K8: 10890 | L8: 2190 | M8: 10000 | Q8: 9906 | W8: =SUM(D8:V8) -> 51976 | X8: 45894 | Y8: 12130 | Z8: =SUM(W8:Y8) -> 110000 | AA8: 10〇+初期1万 | AB8: 未作成 | AC8: =C8-M8 -> 67000
A9: 915 | B9: 菱池重治 | C9: 140000 | D9: 40000 | E9: 5000 | F9: 5000 | G9: 2000 | H9: 10000 | I9: 42900 | J9: -33190 | K9: 7260 | L9: 2190 | M9: 10000 | Q9: 7550 | W9: =SUM(D9:V9) -> 98710 | X9: 31290 | Z9: =SUM(W9:Y9) -> 130000 | AA9: 45974 | AB9: 未作成 | AC9: =C9-M9 -> 130000
A10: 1005 | W10: =SUM(D10:V10) -> 0 | Z10: =SUM(W10:Y10) -> 0 | AB10: 未作成 | AC10: =C10-M10 -> 0
A11: 1006 | B11: 荒木のり子 | C11: 150000 | D11: 40000 | E11: 5000 | F11: 5000 | G11: 2000 | H11: 10000 | I11: 30800 | K11: 0 | L11: 0 | M11: 10000 | W11: =SUM(D11:V11) -> 102800 | Z11: =SUM(W11:Y11) -> 102800 | AA11: 13-15 | AB11: 未作成 | AC11: =C11-M11 -> 140000
A12: 1012 | W12: =SUM(D12:V12) -> 0 | Z12: =SUM(W12:Y12) -> 0 | AB12: 未作成 | AC12: =C12-M12 -> 0
W13: =SUM(D13:V13) -> 0 | Z13: =SUM(W13:Y13) -> 0 | AB13: 未作成 | AC13: =C13-M13 -> 0
A14: ='入居者'!A13 | W14: =SUM(D14:V14) -> 0 | Z14: =SUM(W14:Y14) -> 0 | AC14: =C14-M14 -> 0
W15: =SUM(D15:V15) -> 0 | Z15: =SUM(W15:Y15) -> 0 | AC15: =C15-M15 -> 0
W16: =SUM(D16:V16) -> 0 | Z16: =SUM(W16:Y16) -> 0 | AC16: =C16-M16 -> 0
W17: =SUM(D17:V17) -> 0 | Z17: =SUM(W17:Y17) -> 0 | AC17: =C17-M17 -> 0
W18: =SUM(D18:V18) -> 0 | Z18: =SUM(W18:Y18) -> 0 | AC18: =C18-M18 -> 0
W19: =SUM(D19:V19) -> 0 | Z19: =SUM(W19:Y19) -> 0 | AC19: =C19-M19 -> 0
W20: =SUM(D20:V20) -> 0 | Z20: =SUM(W20:Y20) -> 0 | AC20: =C20-M20 -> 0
W21: =SUM(D21:V21) -> 0 | Z21: =SUM(W21:Y21) -> 0 | AC21: =C21-M21 -> 0
W22: =SUM(D22:V22) -> 0 | Z22: =SUM(W22:Y22) -> 0 | AC22: =C22-M22 -> 0
W23: =SUM(D23:V23) -> 0 | Z23: =SUM(W23:Y23) -> 0 | AC23: =C23-M23 -> 0
W24: =SUM(D24:V24) -> 0 | Z24: =SUM(W24:Y24) -> 0 | AC24: =C24-M24 -> 0
W25: =SUM(D25:V25) -> 0 | Z25: =SUM(W25:Y25) -> 0 | AC25: =C25-M25 -> 0
W26: =SUM(D26:V26) -> 0 | Z26: =SUM(W26:Y26) -> 0 | AC26: =C26-M26 -> 0
... W109: =SUM(D109:V109) -> 0 | Z109: =SUM(W109:Y109) -> 0 | AC109: =C109-M109 -> 0
A110: 合計 | D110: =SUM(D3:D109) -> 280000 | E110: =SUM(E3:E109) -> 35000 | F110: =SUM(F3:F109) -> 35000 | G110: =SUM(G3:G109) -> 14000 | H110: =SUM(H3:H109) -> 70000 | I110: =SUM(I3:I109) -> 142890 | J110: =SUM(J3:J109) -> -116350 | K110: =SUM(K3:K109) -> 25047 | ... V110: =SUM(V3:V109) -> 0 | W110: =SUM(D110:V110) -> 538810 | X110: =SUM(X3:X109) -> 101177 | Y110: =SUM(Y3:Y109) -> 12130 | Z110: =SUM(Z3:Z109) -> 652117

Sheet 202508
A1: 45900 | C1: 請求 | D1: D | E1: E | F1: F | G1: G | H1: H | I1: I | J1: J | K1: K | L1: L | M1: M | N1: N | O1: O | P1: P | Q1: Q | R1: R | S1: S | T1: T | U1: U | V1: V | W1: W | X1: X | Y1: Y | Z1: Z | AA1: AA | AB1: AB
A2: 居室 | B2: 利用者名 | C2: 分納残 | D2: 家賃 | E2: 管理費 | F2: 共益費 | G2: 水道料金 | H2: 定額光熱費 | I2: 食事 | J2: 調整額 | K2: オムツ | L2: 日用品 | M2: 分割支払い | N2: 事務手数料 | O2: デイサービス | P2: 福祉用具 | Q2: しろくま薬局 | R2: 往診診療費 | S2: サポート費 | T2: その他 | W2: 計 | X2: 一部負担(介護) | Y2: 一部負担(看護) | Z2: 合計 | AA2: 備考 | AB2: 請求書 | AC2: 分割残高
A3: 608 | B3: 岡村三男 | D3: 40000 | E3: 5000 | F3: 5000 | G3: 2000 | H3: 10000 | I3: 0 | J3: -2618 | K3: 0 | L3: 0 | M3: 0 | Q3: 3386 | T3: 16500 | W3: =SUM(D3:V3) -> 79268 | X3: 23872 | Z3: =SUM(W3:Y3) -> 103140 | AB3: 未作成 | AC3: =C3-M3 -> 0
A4: 703 | T4: 0 | W4: =SUM(D4:V4) -> 0 | Z4: =SUM(D4:R4) -> 0 | AB4: 未作成 | AC4: =C4-M4 -> 0
A5: 801 | B5: 上村春子 | D5: 40000 | E5: 5000 | F5: 5000 | G5: 2000 | H5: 10000 | I5: 41030 | J5: -16546 | K5: =363*31 -> 11253 | L5: =73*31 -> 2263 | M5: 10000 | T5: 0 | W5: =SUM(D5:V5) -> 110000 | Z5: =SUM(D5:R5) -> 110000 | AA5: 10○+初期1万 | AB5: 未作成 | AC5: =C5-M5 -> -10000
A6: 813 | T6: 0 | W6: =SUM(D6:V6) -> 0 | Z6: =SUM(D6:R6) -> 0 | AB6: 未作成 | AC6: =C6-M6 -> 0
A7: 906 | W7: =SUM(D7:V7) -> 0 | Z7: =SUM(D7:R7) -> 0 | AB7: 未作成 | AC7: =C7-M7 -> 0
A8: 913 | B8: 加藤敬子 | C8: 87000 | D8: 40000 | E8: 5000 | F8: 5000 | G8: 2000 | H8: 10000 | I8: 42130 | J8: -17646 | K8: =363*31 -> 11253 | L8: =73*31 -> 2263 | M8: 10000 | W8: =SUM(D8:V8) -> 110000 | Z8: =SUM(D8:R8) -> 110000 | AA8: 10〇+初期1万 | AB8: 未作成 | AC8: =C8-M8 -> 77000
A9: 915 | B9: 菱池重治 | C9: 150000 | D9: 40000 | E9: 5000 | F9: 5000 | G9: 2000 | H9: 10000 | I9: 44330 | K9: =242*31 -> 7502 | L9: =73*31 -> 2263 | M9: 10000 | T9: 0 | W9: =SUM(D9:V9) -> 126095 | Z9: =SUM(D9:R9) -> 126095 | AB9: 未作成 | AC9: =C9-M9 -> 140000
A10: 1005 | T10: 0 | W10: =SUM(D10:V10) -> 0 | Z10: =SUM(D10:R10) -> 0 | AA10: 13-15 | AB10: 未作成 | AC10: =C10-M10 -> 0
A11: 1006 | B11: 荒木のり子 | C11: 160000 | D11: 40000 | E11: 5000 | F11: 5000 | G11: 2000 | H11: 10000 | I11: 4400 | K11: 0 | L11: 0 | M11: 10000 | N11: 1500 | T11: 0 | W11: =SUM(D11:V11) -> 77900 | Z11: =SUM(D11:R11) -> 77900 | AB11: 未作成 | AC11: =C11-M11 -> 150000
A12: 1012 | W12: =SUM(D12:V12) -> 0 | Z12: =SUM(D12:R12) -> 0 | AA12: 11-13万 | AB12: 未作成 | AC12: =C12-M12 -> 0
W13: =SUM(D13:V13) -> 0 | Z13: =SUM(D13:R13) -> 0 | AB13: 未作成 | AC13: =C13-M13 -> 0
W14: =SUM(D14:V14) -> 0 | Z14: =SUM(D14:R14) -> 0 | AC14: =C14-M14 -> 0
W15: =SUM(D15:V15) -> 0 | Z15: =SUM(D15:R15) -> 0 | AC15: =C15-M15 -> 0
W16: =SUM(D16:V16) -> 0 | Z16: =SUM(D16:R16) -> 0 | AC16: =C16-M16 -> 0
W17: =SUM(D17:V17) -> 0 | Z17: =SUM(D17:R17) -> 0 | AC17: =C17-M17 -> 0
W18: =SUM(D18:V18) -> 0 | Z18: =SUM(D18:R18) -> 0 | AC18: =C18-M18 -> 0
W19: =SUM(D19:V19) -> 0 | Z19: =SUM(D19:R19) -> 0 | AC19: =C19-M19 -> 0
W20: =SUM(D20:V20) -> 0 | Z20: =SUM(D20:R20) -> 0 | AC20: =C20-M20 -> 0
W21: =SUM(D21:V21) -> 0 | Z21: =SUM(D21:R21) -> 0 | AC21: =C21-M21 -> 0
W22: =SUM(D22:V22) -> 0 | Z22: =SUM(D22:R22) -> 0 | AC22: =C22-M22 -> 0
W23: =SUM(D23:V23) -> 0 | Z23: =SUM(D23:R23) -> 0 | AC23: =C23-M23 -> 0
W24: =SUM(D24:V24) -> 0 | Z24: =SUM(D24:R24) -> 0 | AC24: =C24-M24 -> 0
W25: =SUM(D25:V25) -> 0 | Z25: =SUM(D25:R25) -> 0 | AC25: =C25-M25 -> 0
... W109: =SUM(D109:V109) -> 0 | Z109: =SUM(D109:R109) -> 0 | AC109: =C109-M109 -> 0
A110: 合計 | D110: =SUM(D3:D109) -> 200000 | E110: =SUM(E3:E109) -> 25000 | F110: =SUM(F3:F109) -> 25000 | G110: =SUM(G3:G109) -> 10000 | H110: =SUM(H3:H109) -> 50000 | I110: =SUM(I3:I109) -> 131890 | J110: =SUM(J3:J109) -> -36810 | K110: =SUM(K3:K109) -> 30008 | ... V110: =SUM(V3:V109) -> 0 | W110: =SUM(D110:V110) -> 503263 | X110: =SUM(X3:X109) -> 23872 | Y110: =SUM(Y3:Y109) -> 0 | Z110: =SUM(Z3:Z109) -> 527135

Sheet R7.7(作成中)
A1: 45869
A2: 居室 | B2: 利用者名 | C2: 分納残高 | D2: 8月家賃 | E2: 8月管理費 | F2: 8月共益費 | G2: 8月水道料金 | H2: 定額光熱費 | I2: 食事 | J2: オムツ | K2: 日用品 | L2: 福祉用具 | M2: 介護一部負担 | N2: 介護保険料 | O2: 健康保険料 | P2: 分割支払い | Q2: サポート費 | R2: 事務手数料 | S2: 外部利用 | T2: 6月一部負担 | U2: その他 | V2: 合計 | W2: 備考 | X2: 請求書
A3: 608 | V3: =SUM(D3:U3) -> 0
A4: 703 | V4: =SUM(D4:U4) -> 0
A5: 801 | B5: 上村春子 | C5: 160000 | D5: 40000 | E5: 5000 | F5: 5000 | G5: 2000 | H5: 10000 | I5: 20570 | P5: 10000 | T5: 0 | V5: =SUM(D5:U5) -> 92570 | W5: 10○+初期1万 | X5: 作成中 | Y5: 家族郵送
A6: 813 | V6: =SUM(D6:U6) -> 0
A7: 906 | V7: =SUM(D7:U7) -> 0
A8: 913 | B8: 加藤恵子 | C8: 219000 | D8: 40000 | E8: 5000 | F8: 5000 | G8: 2000 | H8: 10000 | I8: 27100 | J8: =363*25 -> 9075 | K8: =73*25 -> 1825 | P8: 10000 | Q8: 0 | T8: 0 | V8: =SUM(D8:U8) -> 110000 | W8: 10〇+初期1万 | X8: 発行済 | Y8: AA
A9: 1005 | V9: =SUM(D9:U9) -> 0
A10: 1006 | V10: =SUM(D10:U10) -> 0
A11: 1012 | V11: =SUM(D11:U11) -> 0
A12: 915 | B12: 菱池重治 | C12: 160000 | D12: 40000 | E12: 5000 | F12: 5000 | G12: 2000 | I12: 2530 | P12: 10000 | V12: =SUM(D12:U12) -> 64530 | W12: 13丸 | X12: 未作成 | Y12: 家族郵送
V13: =SUM(D13:U13) -> 0
V14: =SUM(D14:U14) -> 0
V15: =SUM(D15:U15) -> 0
V16: =SUM(D16:U16) -> 0
V17: =SUM(D17:U17) -> 0
V18: =SUM(D18:U18) -> 0
V19: =SUM(D19:U19) -> 0
V20: =SUM(D20:U20) -> 0
V21: =SUM(D21:U21) -> 0
V22: =SUM(D22:U22) -> 0
V23: =SUM(D23:U23) -> 0
V24: =SUM(D24:U24) -> 0
... V26: =SUM(D26:U26) -> 0
A27: 合計 | D27: =SUM(D3:D26) -> 120000 | E27: =SUM(E3:E26) -> 15000 | F27: =SUM(F3:F26) -> 15000 | G27: =SUM(G3:G26) -> 6000 | H27: =SUM(H3:H26) -> 20000 | I27: =SUM(I3:I26) -> 50200 | J27: =SUM(J3:J26) -> 9075 | K27: =SUM(K3:K26) -> 1825 | ... U27: =SUM(U3:U26) -> 0 | V27: =SUM(D27:U27) -> 267100
